prang/__init__.py
prang/_version.py
prang/relaxng.rng
prang/validation.py
prang/simplification.py
prang/commands.py
prang-0.0.1.dist-info/metadata.json
prang-0.0.1.dist-info/entry_points.txt
prang-0.0.1.dist-info/DESCRIPTION.rst
prang-0.0.1.dist-info/METADATA
prang-0.0.1.dist-info/WHEEL
prang-0.0.1.dist-info/RECORD
prang-0.0.1.dist-info/top_level.txt
