Metadata-Version: 2.0
Name: prang
Version: 0.0.1
Summary: A pure Python RELAX NG validator.
Home-page: https://github.com/tlocke/prang
Author: Tony Locke
Author-email: tlocke@tlocke.org.uk
License: MIT
Keywords: RELAX NG XML schema
Platform: UNKNOWN
Classifier: Development Status :: 4 - Beta
Classifier: Intended Audience :: Developers
Classifier: License :: OSI Approved :: MIT License
Classifier: Programming Language :: Python
Classifier: Programming Language :: Python :: 2
Classifier: Programming Language :: Python :: 2.7
Classifier: Programming Language :: Python :: 3
Classifier: Programming Language :: Python :: 3.4
Classifier: Programming Language :: Python :: Implementation
Classifier: Programming Language :: Python :: Implementation :: CPython
Classifier: Programming Language :: Python :: Implementation :: PyPy
Classifier: Operating System :: OS Independent
Requires-Dist: requests
